lenslet/__init__.py
lenslet/api.py
lenslet/cli.py
lenslet/metadata.py
lenslet/og.py
lenslet/og_cache.py
lenslet/server.py
lenslet/server_models.py
lenslet/server_sync.py
lenslet/thumb_cache.py
lenslet/thumbs.py
lenslet/workspace.py
lenslet/embeddings/__init__.py
lenslet/embeddings/cache.py
lenslet/embeddings/config.py
lenslet/embeddings/detect.py
lenslet/embeddings/embedder.py
lenslet/embeddings/index.py
lenslet/embeddings/io.py
lenslet/frontend/favicon.ico
lenslet/frontend/index.html
lenslet/frontend/assets/index-Dpy6nZNg.css
lenslet/frontend/assets/index-YHZjgv2o.js
lenslet/storage/__init__.py
lenslet/storage/base.py
lenslet/storage/dataset.py
lenslet/storage/local.py
lenslet/storage/memory.py
lenslet/storage/parquet.py
lenslet/storage/progress.py
lenslet/storage/table.py
lenslet-0.2.12.dist-info/METADATA
lenslet-0.2.12.dist-info/WHEEL
lenslet-0.2.12.dist-info/entry_points.txt
lenslet-0.2.12.dist-info/RECORD
