Metadata-Version: 2.4
Name: lenslet
Version: 0.2.12
Summary: Lightweight image gallery server - no database, no files left behind
Project-URL: Homepage, https://github.com/trojblue/lenslet
Project-URL: Repository, https://github.com/trojblue/lenslet
Author-email: yada <trojblue@gmail.com>
License: MIT
Keywords: gallery,image,photos,server,viewer
Classifier: Development Status :: 3 - Alpha
Classifier: Environment :: Console
Classifier: Environment :: Web Environment
Classifier: Framework :: FastAPI
Classifier: Intended Audience :: Developers
Classifier: Intended Audience :: End Users/Desktop
Classifier: License :: OSI Approved :: MIT License
Classifier: Operating System :: OS Independent
Classifier: Programming Language :: Python :: 3
Classifier: Programming Language :: Python :: 3.10
Classifier: Programming Language :: Python :: 3.11
Classifier: Programming Language :: Python :: 3.12
Classifier: Topic :: Multimedia :: Graphics :: Viewers
Requires-Python: >=3.10
Requires-Dist: fastapi>=0.115
Requires-Dist: pillow>=10.4
Requires-Dist: pyarrow>=14.0
Requires-Dist: tqdm>=4.66
Requires-Dist: uvicorn[standard]>=0.30
Provides-Extra: dev
Requires-Dist: httpx>=0.27; extra == 'dev'
Requires-Dist: pytest>=8.0; extra == 'dev'
Provides-Extra: embeddings
Requires-Dist: numpy>=1.26; extra == 'embeddings'
Provides-Extra: embeddings-faiss
Requires-Dist: faiss-cpu>=1.7.4; extra == 'embeddings-faiss'
Requires-Dist: numpy>=1.26; extra == 'embeddings-faiss'
Provides-Extra: s3
Requires-Dist: boto3>=1.34; extra == 's3'
